sanic_sse/__init__.py
sanic_sse/pub_sub.py
sanic_sse/sse.py
sanic_sse-0.3.1.dist-info/LICENSE
sanic_sse-0.3.1.dist-info/WHEEL
sanic_sse-0.3.1.dist-info/METADATA
sanic_sse-0.3.1.dist-info/RECORD
