Metadata-Version: 2.1
Name: sanic-sse
Version: 0.3.1
Summary: Sanic Server-Sent Events extension
Home-page: https://github.com/inn0kenty/sanic_sse
License: MIT
Author: Innokenty Lebedev
Requires-Python: >=3.5,<4.0
Classifier: Framework :: AsyncIO
Classifier: Intended Audience :: Developers
Classifier: License :: OSI Approved :: MIT License
Classifier: Programming Language :: Python :: 3
Classifier: Programming Language :: Python :: 3.5
Classifier: Programming Language :: Python :: 3.6
Classifier: Programming Language :: Python :: 3.7
Classifier: Programming Language :: Python :: 3.8
Classifier: Programming Language :: Python :: 3.9
Classifier: Topic :: Internet :: WWW/HTTP
Requires-Dist: sanic
Project-URL: Repository, https://github.com/inn0kenty/sanic_sse
